[
  [
    { "traitClass": "Skin", "trait": "Blue", "zIndex": 2 },
    { "traitClass": "Mouth", "trait": "Mouth1", "zIndex": 3 },
    { "traitClass": "Scars", "trait": "_Scar1", "zIndex": 4 },
    { "traitClass": "Hair", "trait": "Hair3white", "zIndex": 5 },
    { "traitClass": "Beards", "trait": "Beard2white", "zIndex": 6 },
    { "traitClass": "Eyebrows", "trait": "Eyebrows1white", "zIndex": 7 },
    { "traitClass": "Eyepatch", "trait": "_Eyepatch1", "zIndex": 8 },
    { "traitClass": "Earings", "trait": "Earings4", "zIndex": 9 }
  ]
]
